<?xml version="1.0" encoding="UTF-8"?>
<solver>
  <!-- Domain model configuration -->
  <scanAnnotatedClasses/>

  <!-- Score configuration -->
  <scoreDirectorFactory>
    <!--<easyScoreCalculatorClass>br.com.caelum.escalonadorteste.modelo.CalculadorDeScoreDeAlocacao</easyScoreCalculatorClass>-->
    <scoreDrl>escalonador/conf/RegrasEscalonamento.drl</scoreDrl>
  </scoreDirectorFactory>

  <!-- Optimization algorithms configuration -->
  <constructionHeuristic>
    <constructionHeuristicType>FIRST_FIT</constructionHeuristicType>
  </constructionHeuristic>
  <localSearch>
    <localSearchType>LATE_ACCEPTANCE</localSearchType>
  </localSearch>
  
  <termination>
    <secondsSpentLimit>60</secondsSpentLimit>
  </termination>
</solver>